pinger/__init__.py
pinger/admin.py
pinger/app_settings.py
pinger/apps.py
pinger/auth_hooks.py
pinger/cogs.py
pinger/exceptions.py
pinger/models.py
pinger/providers.py
pinger/tasks.py
pinger/management/__init__.py
pinger/management/commands/__init.py
pinger/management/commands/pinger_setup.py
pinger/management/commands/pinger_stats.py
pinger/migrations/0001_initial.py
pinger/migrations/0002_create_ping_types.py
pinger/migrations/0003_auto_20211108_0024.py
pinger/migrations/0004_create_more_types.py
pinger/migrations/0005_pingerconfig.py
pinger/migrations/0006_create_settings.py
pinger/migrations/0007_create_more_types_again.py
pinger/migrations/0008_mutedstructure.py
pinger/migrations/0009_add_more_types.py
pinger/migrations/0010_pingerconfig_discord_mute_channels.py
pinger/migrations/0011_auto_20220203_0840.py
pinger/migrations/0012_fuelpingrecord_last_message.py
pinger/migrations/0013_discordwebhook_no_at_pings.py
pinger/migrations/0014_structurelothreshold.py
pinger/migrations/0015_add_more_types.py
pinger/migrations/0016_add_more_types.py
pinger/migrations/0017_pingerconfig_attack_command_output_id.py
pinger/migrations/0018_add_more_types.py
pinger/migrations/0019_discordwebhook_gas_pings.py
pinger/migrations/0020_add_more_types.py
pinger/migrations/0021_add_more_types.py
pinger/migrations/0022_add_more_types.py
pinger/migrations/0023_add_more_types.py
pinger/migrations/__init__.py
pinger/notifications/__init__.py
pinger/notifications/base.py
pinger/notifications/character.py
pinger/notifications/corporate.py
pinger/notifications/helpers.py
pinger/notifications/moons.py
pinger/notifications/orbital.py
pinger/notifications/projects.py
pinger/notifications/sov.py
pinger/notifications/structure.py
pinger/notifications/towers.py
pinger/notifications/war.py
pinger/tests/__init__.py
pinger/tests/test_notifications_orbital.py
allianceauth_corptools_pinger-0.6.2.dist-info/licenses/LICENSE
allianceauth_corptools_pinger-0.6.2.dist-info/WHEEL
allianceauth_corptools_pinger-0.6.2.dist-info/METADATA
allianceauth_corptools_pinger-0.6.2.dist-info/RECORD
